semvermanager/__init__.py
semvermanager/__main__.py
semvermanager/command.py
semvermanager/version.py
semvermanager-1.0.9.dist-info/LICENSE
semvermanager-1.0.9.dist-info/METADATA
semvermanager-1.0.9.dist-info/WHEEL
semvermanager-1.0.9.dist-info/entry_points.txt
semvermanager-1.0.9.dist-info/top_level.txt
semvermanager-1.0.9.dist-info/RECORD
