Metadata-Version: 2.1
Name: semvermanager
Version: 1.0.9
Summary: semvermamager implements a restricted subset of the SEMVER standard
Home-page: https://github.com/jdrumgoole/semvermanager
Author: Joe Drumgoole
Author-email: joe@joedrumgoole.com
License: MIT
Platform: UNKNOWN
Classifier: License :: OSI Approved :: MIT License
Classifier: Programming Language :: Python
Classifier: Programming Language :: Python :: 3
Classifier: Programming Language :: Python :: 3.6
Classifier: Programming Language :: Python :: Implementation :: CPython
Classifier: Programming Language :: Python :: Implementation :: PyPy
Requires-Python: >=3.6.0
